number_tools/__init__.py
number_tools/converters.py
number_tools-0.1.0.dist-info/LICENSE.txt
number_tools-0.1.0.dist-info/METADATA
number_tools-0.1.0.dist-info/WHEEL
number_tools-0.1.0.dist-info/top_level.txt
number_tools-0.1.0.dist-info/RECORD
